{
  "$schema": "https://raw.githubusercontent.com/Computational-Biology-Aachen/mxl-schemas/main/v1/steady-state-model.schema.json",
  "spec_version": "1.0",
  "kind": "steady-state",
  "model_id": "fvcb1980",
  "model": {
    "parameters": {
      "Ci": {
        "value": {
          "type": "Num",
          "value": 500
        },
        "displayName": "Ci",
        "texName": "C_i"
      },
      "vcmax": {
        "value": {
          "type": "Num",
          "value": 80
        },
        "texName": "V_{cmax}"
      },
      "kc": {
        "value": {
          "type": "Num",
          "value": 259
        },
        "texName": "K_c"
      },
      "ko": {
        "value": {
          "type": "Num",
          "value": 179
        },
        "texName": "K_o"
      },
      "ccp": {
        "value": {
          "type": "Num",
          "value": 38.6
        },
        "texName": "\\Gamma^*"
      },
      "rl": {
        "value": {
          "type": "Num",
          "value": 1
        },
        "texName": "R_d"
      },
      "alpha": {
        "value": {
          "type": "Num",
          "value": 0
        },
        "texName": "\\alpha"
      },
      "o": {
        "value": {
          "type": "Num",
          "value": 210
        },
        "displayName": "O₂",
        "texName": "O",
        "slider": {
          "min": "100",
          "max": "500",
          "step": "1"
        }
      },
      "j": {
        "value": {
          "type": "Num",
          "value": 124
        },
        "displayName": "J",
        "texName": "J",
        "slider": {
          "min": "50",
          "max": "300",
          "step": "1"
        }
      },
      "tp": {
        "value": {
          "type": "Num",
          "value": 15
        },
        "displayName": "Tp",
        "texName": "T_p",
        "slider": {
          "min": "5",
          "max": "50",
          "step": "1"
        }
      }
    },
    "derived": {
      "wc": {
        "fn": {
          "type": "Divide",
          "children": [
            {
              "type": "Mul",
              "children": [
                {
                  "type": "Name",
                  "value": "Ci"
                },
                {
                  "type": "Name",
                  "value": "vcmax"
                }
              ]
            },
            {
              "type": "Add",
              "children": [
                {
                  "type": "Name",
                  "value": "Ci"
                },
                {
                  "type": "Mul",
                  "children": [
                    {
                      "type": "Name",
                      "value": "kc"
                    },
                    {
                      "type": "Add",
                      "children": [
                        {
                          "type": "Num",
                          "value": 1
                        },
                        {
                          "type": "Divide",
                          "children": [
                            {
                              "type": "Name",
                              "value": "o"
                            },
                            {
                              "type": "Name",
                              "value": "ko"
                            }
                          ]
                        }
                      ]
                    }
                  ]
                }
              ]
            }
          ]
        },
        "displayName": "Wc",
        "texName": "W_c"
      },
      "wj": {
        "fn": {
          "type": "Divide",
          "children": [
            {
              "type": "Mul",
              "children": [
                {
                  "type": "Name",
                  "value": "Ci"
                },
                {
                  "type": "Name",
                  "value": "j"
                }
              ]
            },
            {
              "type": "Add",
              "children": [
                {
                  "type": "Mul",
                  "children": [
                    {
                      "type": "Num",
                      "value": 4
                    },
                    {
                      "type": "Name",
                      "value": "Ci"
                    }
                  ]
                },
                {
                  "type": "Mul",
                  "children": [
                    {
                      "type": "Num",
                      "value": 8
                    },
                    {
                      "type": "Name",
                      "value": "ccp"
                    }
                  ]
                }
              ]
            }
          ]
        },
        "displayName": "Wj",
        "texName": "W_j"
      },
      "wp": {
        "fn": {
          "type": "Piecewise",
          "children": [
            {
              "type": "Num",
              "value": 100
            },
            {
              "type": "LessEqual",
              "children": [
                {
                  "type": "Name",
                  "value": "Ci"
                },
                {
                  "type": "Mul",
                  "children": [
                    {
                      "type": "Name",
                      "value": "ccp"
                    },
                    {
                      "type": "Add",
                      "children": [
                        {
                          "type": "Num",
                          "value": 1
                        },
                        {
                          "type": "Mul",
                          "children": [
                            {
                              "type": "Num",
                              "value": 3
                            },
                            {
                              "type": "Name",
                              "value": "alpha"
                            }
                          ]
                        }
                      ]
                    }
                  ]
                }
              ]
            },
            {
              "type": "Divide",
              "children": [
                {
                  "type": "Mul",
                  "children": [
                    {
                      "type": "Num",
                      "value": 3
                    },
                    {
                      "type": "Name",
                      "value": "Ci"
                    },
                    {
                      "type": "Name",
                      "value": "tp"
                    }
                  ]
                },
                {
                  "type": "Minus",
                  "children": [
                    {
                      "type": "Name",
                      "value": "Ci"
                    },
                    {
                      "type": "Mul",
                      "children": [
                        {
                          "type": "Name",
                          "value": "ccp"
                        },
                        {
                          "type": "Add",
                          "children": [
                            {
                              "type": "Num",
                              "value": 1
                            },
                            {
                              "type": "Mul",
                              "children": [
                                {
                                  "type": "Num",
                                  "value": 3
                                },
                                {
                                  "type": "Name",
                                  "value": "alpha"
                                }
                              ]
                            }
                          ]
                        }
                      ]
                    }
                  ]
                }
              ]
            }
          ]
        },
        "displayName": "Wp",
        "texName": "W_p"
      },
      "vc": {
        "fn": {
          "type": "Min",
          "children": [
            {
              "type": "Name",
              "value": "wc"
            },
            {
              "type": "Name",
              "value": "wj"
            },
            {
              "type": "Name",
              "value": "wp"
            }
          ]
        },
        "displayName": "Vc",
        "texName": "V_c"
      },
      "an": {
        "fn": {
          "type": "Minus",
          "children": [
            {
              "type": "Mul",
              "children": [
                {
                  "type": "Name",
                  "value": "vc"
                },
                {
                  "type": "Minus",
                  "children": [
                    {
                      "type": "Num",
                      "value": 1
                    },
                    {
                      "type": "Divide",
                      "children": [
                        {
                          "type": "Name",
                          "value": "ccp"
                        },
                        {
                          "type": "Name",
                          "value": "Ci"
                        }
                      ]
                    }
                  ]
                }
              ]
            },
            {
              "type": "Name",
              "value": "rl"
            }
          ]
        },
        "displayName": "An",
        "texName": "A_n"
      }
    }
  }
}
